activejson/__init__.py
activejson/flatten_json_tools.py
activejson/frozen_json.py
activejson-0.4.0.dist-info/LICENSE
activejson-0.4.0.dist-info/WHEEL
activejson-0.4.0.dist-info/METADATA
activejson-0.4.0.dist-info/RECORD
