Metadata-Version: 2.1
Name: activejson
Version: 0.4.0
Summary: A convenient library to deal with large json data
License: MIT
Author: Daniel Omar Vergara Pérez
Author-email: daniel.omar.vergara@gmail.com
Requires-Python: >=3.6,<4.0
Classifier: License :: OSI Approved :: MIT License
Classifier: Programming Language :: Python :: 3
Classifier: Programming Language :: Python :: 3.5
Classifier: Programming Language :: Python :: 3.6
Classifier: Programming Language :: Python :: 3.7
Classifier: Programming Language :: Python :: 3.8
Classifier: Programming Language :: Python :: Implementation :: CPython
Classifier: Programming Language :: Python :: Implementation :: PyPy
